gdebs/__init__.py
gdebs/core/__init__.py
gdebs/core/animals.py
gdebs/core/gene_drive.py
gdebs/core/populations.py
gdebs/legacy/app.py
gdebs/legacy/src/__init__.py
gdebs/legacy/src/animal_patch.py
gdebs/legacy/src/simulation.py
gdebs/simulation/__init__.py
gdebs/simulation/simulation.py
gdebs/utils/__init__.py
gdebs/utils/settings.py
gdebs/visualization/__init__.py
gdebs/visualization/plotting.py
gdebs-1.0.2.dist-info/METADATA
gdebs-1.0.2.dist-info/WHEEL
gdebs-1.0.2.dist-info/licenses/LICENSE
gdebs-1.0.2.dist-info/RECORD
