Metadata-Version: 2.4
Name: gdebs
Version: 1.0.2
Summary: An event based simulation package for observing the spread of a gene drive in an animal population
Project-URL: Homepage, https://github.com/rsnarang/gdebs
License-Expression: GPL-3.0-or-later
License-File: LICENSE
Classifier: Operating System :: OS Independent
Classifier: Programming Language :: Python :: 3
Requires-Python: >=3.13
